whatshouldido.py
whatshouldido-0.1.12.dist-info/entry_points.txt
whatshouldido-0.1.12.dist-info/LICENSE
whatshouldido-0.1.12.dist-info/WHEEL
whatshouldido-0.1.12.dist-info/METADATA
whatshouldido-0.1.12.dist-info/RECORD
