Metadata-Version: 2.1
Name: whatshouldido
Version: 0.1.12
Summary: Allows to see sorted by date TODOS from code
Author-email: djbios <dorandval@gmail.com>
Classifier: License :: OSI Approved :: MIT License
Requires-Dist: termcolor
Requires-Dist: tabulate
Requires-Dist: GitPython
Requires-Dist: click
Project-URL: Home, https://djbios.org
